gPhoton/CalUtils.py
gPhoton/CalibrationTools.py
gPhoton/FileUtils.py
gPhoton/MCUtils.py
gPhoton/PhotonPipe.py
gPhoton/__init__.py
gPhoton/curvetools.py
gPhoton/dbasetools.py
gPhoton/gAperture.py
gPhoton/gCalrun.py
gPhoton/gFind.py
gPhoton/gMap.py
gPhoton/gPipeline.py
gPhoton/gQuery.py
gPhoton/galextools.py
gPhoton/gnomonic.py
gPhoton/gphoton_args.py
gPhoton/gphoton_utils.py
gPhoton/imagetools.py
gPhoton/regtestutils.py
gPhoton/cal/__init__.py
gPhoton/tests/__init__.py
gPhoton/tests/_test_gAperture_regr.py
gPhoton/tests/_test_gMap_regr.py
gPhoton/tests/test_CalibrationTools.py
gPhoton/tests/test_MCUtils.py
gPhoton/tests/test_args.py
gPhoton/tests/test_curvetools.py
gPhoton/tests/test_dbasetools.py
gPhoton/tests/test_gFind_regr.py
gPhoton/tests/test_gQuery.py
gPhoton/tests/test_galextools.py
gPhoton/tests/test_imagetools.py
gPhoton/tests/regtest/more_test.py
gPhoton/tests/regtest/regtest.py
gphoton_astro-1.0.4.dist-info/licenses/LICENSE
gphoton_astro-1.0.4.dist-info/METADATA
gphoton_astro-1.0.4.dist-info/WHEEL
gphoton_astro-1.0.4.dist-info/top_level.txt
gphoton_astro-1.0.4.dist-info/RECORD
