Metadata-Version: 2.4
Name: gPhoton-astro
Version: 1.0.4
Summary: A modified version of gPhoton for astrophysical data analysis
Author-email: Joysankar Majumdar <j.majumdar@uw.edu.pl>
License: MIT
Project-URL: Homepage, https://github.com/joysankar-astro/gPhoton
Project-URL: Issues, https://github.com/joysankar-astro/gPhoton/issues
Requires-Python: >=3.8
License-File: LICENSE
Requires-Dist: numpy
Requires-Dist: pandas
Requires-Dist: astropy
Requires-Dist: requests
Requires-Dist: scipy
Dynamic: license-file
